datastacks/__init__.py
datastacks/augment.py
datastacks/create.py
datastacks/helpers.py
datastacks/residuals.py
datastacks/stack_dataset.py
datastacks-0.0.0.1.dist-info/LICENSE
datastacks-0.0.0.1.dist-info/METADATA
datastacks-0.0.0.1.dist-info/WHEEL
datastacks-0.0.0.1.dist-info/top_level.txt
datastacks-0.0.0.1.dist-info/RECORD
