Metadata-Version: 2.1
Name: datastacks
Version: 0.0.0.1
Summary: A tool for parametrized loading from H5 datasets
Home-page: https://github.com/supersergiy/datastacks
Author: Sergiy Popovych
Author-email: sergiy.popovich@gmail.com
License: UNKNOWN
Platform: UNKNOWN
Requires-Dist: torch
Requires-Dist: torchvision
Requires-Dist: numpy
